neatlogs/__init__.py
neatlogs/core.py
neatlogs/requirements.txt
neatlogs/semconv.py
neatlogs/stream_wrapper.py
neatlogs/token_counting.py
neatlogs/utils.py
neatlogs/event_handlers/__init__.py
neatlogs/event_handlers/anthropic.py
neatlogs/event_handlers/azure.py
neatlogs/event_handlers/base.py
neatlogs/event_handlers/crewai.py
neatlogs/event_handlers/google_genai.py
neatlogs/event_handlers/langchain.py
neatlogs/event_handlers/langgraph.py
neatlogs/event_handlers/litellm.py
neatlogs/event_handlers/openai.py
neatlogs/instrumentation/__init__.py
neatlogs/instrumentation/manager.py
neatlogs/instrumentation/patchers.py
neatlogs/integration/__init__.py
neatlogs/integration/callbacks/__init__.py
neatlogs/integration/callbacks/langchain/__init__.py
neatlogs/integration/callbacks/langchain/callback.py
neatlogs-1.1.8.dist-info/licenses/LICENSE
neatlogs-1.1.8.dist-info/METADATA
neatlogs-1.1.8.dist-info/WHEEL
neatlogs-1.1.8.dist-info/top_level.txt
neatlogs-1.1.8.dist-info/RECORD
