Metadata-Version: 2.4
Name: neatlogs
Version: 1.1.8
Summary: A Python package for extracting and managing LLM logs to build a collaborative workspace
Author-email: Neatlogs <hello@neatlogs.com>
License: MIT
Project-URL: Homepage, https://github.com/NeatLogs/neatlogs
Project-URL: Repository, https://github.com/NeatLogs/neatlogs.git
Project-URL: Issues, https://github.com/NeatLogs/neatlogs/issues
Project-URL: Documentation, https://docs.neatlogs.com/
Keywords: llm,tracking,monitoring,logging,ai,machine-learning,observability,collboration
Classifier: Development Status :: 4 - Beta
Classifier: Intended Audience :: Developers
Classifier: License :: OSI Approved :: MIT License
Classifier: Operating System :: OS Independent
Classifier: Programming Language :: Python :: 3
Classifier: Programming Language :: Python :: 3.8
Classifier: Programming Language :: Python :: 3.9
Classifier: Programming Language :: Python :: 3.10
Classifier: Programming Language :: Python :: 3.11
Classifier: Programming Language :: Python :: 3.12
Classifier: Programming Language :: Python :: 3.13
Classifier: Topic :: Software Development :: Libraries :: Python Modules
Classifier: Topic :: Scientific/Engineering :: Artificial Intelligence
Classifier: Topic :: System :: Logging
Classifier: Topic :: System :: Monitoring
Requires-Python: >=3.8
License-File: LICENSE
Dynamic: license-file
